chimera_sandbox_extensions/__init__.py
chimera_sandbox_extensions-0.1.42.dist-info/METADATA
chimera_sandbox_extensions-0.1.42.dist-info/WHEEL
chimera_sandbox_extensions-0.1.42.dist-info/top_level.txt
chimera_sandbox_extensions-0.1.42.dist-info/RECORD
