Metadata-Version: 2.4
Name: chimera_sandbox_extensions
Version: 0.1.42
Summary: Helper module for Chimera sandbox
